MANIFEST.in
README.md
jingerly.py
setup.py
bin/jingerly
jingerly.egg-info/PKG-INFO
jingerly.egg-info/SOURCES.txt
jingerly.egg-info/dependency_links.txt
jingerly.egg-info/requires.txt
jingerly.egg-info/top_level.txt