Metadata-Version: 1.1
Name: jingerly
Version: 0.0.3
Summary: Project templating using Jinja2.
Home-page: https://github.com/WilliamMayor/jingerly
Author: William Mayor
Author-email: jinjerly@williammayor.co.uk
License: MIT
Keywords: project management template
Platform: UNKNOWN
Classifier: Development Status :: 3 - Alpha
Classifier: Environment :: Console
Classifier: Intended Audience :: Developers
Classifier: License :: OSI Approved :: MIT License
Classifier: Natural Language :: English
Classifier: Topic :: Software Development :: Code Generators
